{"numFailedTestSuites":0,"numFailedTests":0,"numPassedTestSuites":1,"numPassedTests":10,"numPendingTestSuites":0,"numPendingTests":0,"numRuntimeErrorTestSuites":0,"numTodoTests":0,"numTotalTestSuites":1,"numTotalTests":10,"openHandles":[],"snapshot":{"added":0,"didUpdate":false,"failure":false,"filesAdded":0,"filesRemoved":0,"filesRemovedList":[],"filesUnmatched":0,"filesUpdated":0,"matched":0,"total":0,"unchecked":0,"uncheckedKeysByFile":[],"unmatched":0,"updated":0},"startTime":1714143800125,"success":true,"testResults":[{"assertionResults":[{"ancestorTitles":["Emeklilikte Yaşa Takılanlar(EYT) Hesabı  Testleri"],"duration":12,"failureDetails":[],"failureMessages":[],"fullName":"Emeklilikte Yaşa Takılanlar(EYT) Hesabı  Testleri Fonksiyonun dönüş değeri array mi?","invocations":1,"location":null,"numPassingAsserts":1,"retryReasons":[],"status":"passed","title":"Fonksiyonun dönüş değeri array mi?"},{"ancestorTitles":["Emeklilikte Yaşa Takılanlar(EYT) Hesabı  Testleri"],"duration":2,"failureDetails":[],"failureMessages":[],"fullName":"Emeklilikte Yaşa Takılanlar(EYT) Hesabı  Testleri Fonksiyonun dönüş değeri 3 elemanlı mı","invocations":1,"location":null,"numPassingAsserts":2,"retryReasons":[],"status":"passed","title":"Fonksiyonun dönüş değeri 3 elemanlı mı"},{"ancestorTitles":["Emeklilikte Yaşa Takılanlar(EYT) Hesabı  Testleri"],"duration":2,"failureDetails":[],"failureMessages":[],"fullName":"Emeklilikte Yaşa Takılanlar(EYT) Hesabı  Testleri Fonksiyonun dönüş değerinin ilk elemanı bir array mi?","invocations":1,"location":null,"numPassingAsserts":3,"retryReasons":[],"status":"passed","title":"Fonksiyonun dönüş değerinin ilk elemanı bir array mi?"},{"ancestorTitles":["Emeklilikte Yaşa Takılanlar(EYT) Hesabı  Testleri"],"duration":1,"failureDetails":[],"failureMessages":[],"fullName":"Emeklilikte Yaşa Takılanlar(EYT) Hesabı  Testleri Fonksiyonun dönüş değerinin ikinci elemanı bir array mi?","invocations":1,"location":null,"numPassingAsserts":3,"retryReasons":[],"status":"passed","title":"Fonksiyonun dönüş değerinin ikinci elemanı bir array mi?"},{"ancestorTitles":["Emeklilikte Yaşa Takılanlar(EYT) Hesabı  Testleri"],"duration":1,"failureDetails":[],"failureMessages":[],"fullName":"Emeklilikte Yaşa Takılanlar(EYT) Hesabı  Testleri Fonksiyonun dönüş değerinin son elemanı bir number mı?","invocations":1,"location":null,"numPassingAsserts":1,"retryReasons":[],"status":"passed","title":"Fonksiyonun dönüş değerinin son elemanı bir number mı?"},{"ancestorTitles":["Emeklilikte Yaşa Takılanlar(EYT) Hesabı  Testleri"],"duration":2,"failureDetails":[],"failureMessages":[],"fullName":"Emeklilikte Yaşa Takılanlar(EYT) Hesabı  Testleri 1999 öncesi sigorta kaydını kontrol ediyor mu?","invocations":1,"location":null,"numPassingAsserts":1,"retryReasons":[],"status":"passed","title":"1999 öncesi sigorta kaydını kontrol ediyor mu?"},{"ancestorTitles":["Emeklilikte Yaşa Takılanlar(EYT) Hesabı  Testleri"],"duration":2,"failureDetails":[],"failureMessages":[],"fullName":"Emeklilikte Yaşa Takılanlar(EYT) Hesabı  Testleri 5000 prim gününü doğru kontrol ediyor mu?","invocations":1,"location":null,"numPassingAsserts":1,"retryReasons":[],"status":"passed","title":"5000 prim gününü doğru kontrol ediyor mu?"},{"ancestorTitles":["Emeklilikte Yaşa Takılanlar(EYT) Hesabı  Testleri"],"duration":1,"failureDetails":[],"failureMessages":[],"fullName":"Emeklilikte Yaşa Takılanlar(EYT) Hesabı  Testleri Kadın çalışanlar için 20 yıl kontrolünü yapıyor mu?","invocations":1,"location":null,"numPassingAsserts":1,"retryReasons":[],"status":"passed","title":"Kadın çalışanlar için 20 yıl kontrolünü yapıyor mu?"},{"ancestorTitles":["Emeklilikte Yaşa Takılanlar(EYT) Hesabı  Testleri"],"duration":1,"failureDetails":[],"failureMessages":[],"fullName":"Emeklilikte Yaşa Takılanlar(EYT) Hesabı  Testleri Erkek çalışanlar için 25 yıl kontrolünü yapıyor mu?","invocations":1,"location":null,"numPassingAsserts":1,"retryReasons":[],"status":"passed","title":"Erkek çalışanlar için 25 yıl kontrolünü yapıyor mu?"},{"ancestorTitles":["Emeklilikte Yaşa Takılanlar(EYT) Hesabı  Testleri"],"duration":4,"failureDetails":[],"failureMessages":[],"fullName":"Emeklilikte Yaşa Takılanlar(EYT) Hesabı  Testleri Şirket çalışanları için doğru hesaplama yapıyor mu?","invocations":1,"location":null,"numPassingAsserts":1,"retryReasons":[],"status":"passed","title":"Şirket çalışanları için doğru hesaplama yapıyor mu?"}],"endTime":1714143803905,"message":"","name":"/home/projects/vitejs-vite-t379fj/index.test.js","startTime":1714143800996,"status":"passed","summary":""}],"wasInterrupted":false}
